rustmfx-0.1.4.dist-info/METADATA
rustmfx-0.1.4.dist-info/WHEEL
rustmfx/__init__.py
rustmfx/rustmfx.cpython-313-x86_64-linux-gnu.so
rustmfx-0.1.4.dist-info/RECORD
