Metadata-Version: 2.4
Name: rustmfx
Version: 0.1.4
Classifier: Programming Language :: Rust
Classifier: Programming Language :: Python :: Implementation :: CPython
Classifier: Programming Language :: Python :: Implementation :: PyPy
Requires-Dist: numpy>=1.24.0
Requires-Dist: pandas>=1.0.0
Summary: A Rust-based Statistics and ML package, callable from Python.
Keywords: rust,python,Machine Learning,Statistics,pyo3
Author-email: Luke Brosnan <luke.brosnan.cbc@gmail.com>
License: MIT
Requires-Python: >=3.8
Project-URL: Source Code, https://github.com/luke-brosnan-cbc/RuSTATS
